LICENSE
MANIFEST.in
README.md
README.rst
setup.py
numpy_fracadf/__init__.py
numpy_fracadf/fracadf1.py
numpy_fracadf/fracadf2.py
numpy_fracadf.egg-info/PKG-INFO
numpy_fracadf.egg-info/SOURCES.txt
numpy_fracadf.egg-info/dependency_links.txt
numpy_fracadf.egg-info/requires.txt
numpy_fracadf.egg-info/top_level.txt
numpy_fracadf.egg-info/zip-safe