Metadata-Version: 1.2
Name: numpy-fracadf
Version: 0.4.2
Summary: Determine fractal order by the ADF test
Home-page: http://github.com/ulf1/fracadf
Author: Ulf Hamster
Author-email: 554c46@gmail.com
License: Apache License 2.0
Platform: UNKNOWN
Requires-Python: >=3.6
